notificationapi_python_server_sdk/__init__.py
notificationapi_python_server_sdk/notificationapi.py
notificationapi_python_server_sdk-2.0.1.dist-info/LICENSE
notificationapi_python_server_sdk-2.0.1.dist-info/METADATA
notificationapi_python_server_sdk-2.0.1.dist-info/WHEEL
notificationapi_python_server_sdk-2.0.1.dist-info/top_level.txt
notificationapi_python_server_sdk-2.0.1.dist-info/RECORD
