Metadata-Version: 2.1
Name: notificationapi-python-server-sdk
Version: 2.0.1
Summary: NotificationAPI SDK for server-side (back-end) Python projects.
Home-page: https://github.com/notificationapi-com/notificationapi_python_server_sdk
Author: Sahand Seifi, Mohammad Asadi
Author-email: sahand@notificationspi.com, mohammad@notificationspi.com
License: MIT license
Keywords: notificationapi_python_server_sdk
Platform: UNKNOWN
Classifier: Development Status :: 2 - Pre-Alpha
Classifier: Intended Audience :: Developers
Classifier: License :: OSI Approved :: MIT License
Classifier: Natural Language :: English
Classifier: Programming Language :: Python :: 3
Classifier: Programming Language :: Python :: 3.6
Classifier: Programming Language :: Python :: 3.7
Classifier: Programming Language :: Python :: 3.8
Classifier: Programming Language :: Python :: 3.9
Requires-Python: >=3.6
License-File: LICENSE
